str_or_none/__init__.py
str_or_none-0.1.0.dist-info/LICENSE
str_or_none-0.1.0.dist-info/METADATA
str_or_none-0.1.0.dist-info/WHEEL
str_or_none-0.1.0.dist-info/RECORD
